{
  "klass": "Specie",
  "id": 1004,
  "dbSymbol": "chiyu",
  "forms": [
    {
      "form": 0,
      "height": 0.4,
      "weight": 4.9,
      "type1": "dark",
      "type2": "fire",
      "baseHp": 55,
      "baseAtk": 80,
      "baseDfe": 80,
      "baseAts": 135,
      "baseDfs": 120,
      "baseSpd": 100,
      "evHp": 0,
      "evAtk": 0,
      "evDfe": 0,
      "evAts": 3,
      "evDfs": 0,
      "evSpd": 0,
      "evolutions": [],
      "experienceType": 2,
      "baseExperience": 285,
      "baseLoyalty": 0,
      "catchRate": 6,
      "femaleRate": -1,
      "breedGroups": [
        15,
        0
      ],
      "hatchSteps": 6400,
      "babyDbSymbol": "chiyu",
      "babyForm": 0,
      "itemHeld": [
        {
          "dbSymbol": "none",
          "chance": 0
        },
        {
          "dbSymbol": "none",
          "chance": 0
        }
      ],
      "abilities": [
        "beads_of_ruin",
        "beads_of_ruin",
        "beads_of_ruin"
      ],
      "frontOffsetY": 0,
      "resources": {
        "icon": "1004_00",
        "iconShiny": "1004_00",
        "front": "1004_00",
        "back": "1004_00",
        "frontShiny": "1004_00",
        "backShiny": "1004_00",
        "frontF": "1004f_00",
        "backF": "1004f_00",
        "frontShinyF": "1004f_00",
        "backShinyF": "1004f_00",
        "footprint": "1004_00",
        "character": "1004_00",
        "characterF": "1004f_00",
        "characterShiny": "1004s_00",
        "characterShinyF": "1004fs_00",
        "cry": "1004cry_00.ogg",
        "hasFemale": false
      },
      "moveSet": [],
      "formTextId": {
        "name": 1205,
        "description": 0
      }
    }
  ]
}