{
  "klass": "Specie",
  "id": 605,
  "dbSymbol": "elgyem",
  "forms": [
    {
      "form": 0,
      "height": 0.5,
      "weight": 9.0,
      "type1": "psychic",
      "type2": "__undef__",
      "baseHp": 55,
      "baseAtk": 55,
      "baseDfe": 55,
      "baseAts": 85,
      "baseDfs": 55,
      "baseSpd": 30,
      "evHp": 0,
      "evAtk": 0,
      "evDfe": 0,
      "evAts": 1,
      "evDfs": 0,
      "evSpd": 0,
      "evolutions": [
        {
          "dbSymbol": "beheeyem",
          "form": 0,
          "conditions": [
            {
              "type": "minLevel",
              "value": 42
            }
          ]
        }
      ],
      "experienceType": 1,
      "baseExperience": 67,
      "baseLoyalty": 50,
      "catchRate": 255,
      "femaleRate": 50.0,
      "breedGroups": [
        8,
        0
      ],
      "hatchSteps": 2560,
      "babyDbSymbol": "elgyem",
      "babyForm": 0,
      "itemHeld": [
        {
          "dbSymbol": "none",
          "chance": 0
        },
        {
          "dbSymbol": "none",
          "chance": 0
        }
      ],
      "abilities": [
        "telepathy",
        "synchronize",
        "analytic"
      ],
      "frontOffsetY": 0,
      "resources": {
        "icon": "605",
        "iconShiny": "605",
        "front": "605",
        "back": "605",
        "frontShiny": "605",
        "backShiny": "605",
        "frontF": "605f",
        "backF": "605f",
        "frontShinyF": "605f",
        "backShinyF": "605f",
        "footprint": "605",
        "character": "605",
        "characterF": "605f",
        "characterShiny": "605s",
        "characterShinyF": "605fs",
        "cry": "605cry.ogg",
        "hasFemale": false
      },
      "moveSet": [],
      "formTextId": {
        "name": 252,
        "description": 0
      }
    }
  ]
}