{
  "klass": "Specie",
  "id": 1022,
  "dbSymbol": "ironboulder",
  "forms": [
    {
      "form": 0,
      "height": 1.5,
      "weight": 162.5,
      "type1": "rock",
      "type2": "psychic",
      "baseHp": 90,
      "baseAtk": 120,
      "baseDfe": 80,
      "baseAts": 68,
      "baseDfs": 108,
      "baseSpd": 124,
      "evHp": 0,
      "evAtk": 0,
      "evDfe": 0,
      "evAts": 0,
      "evDfs": 0,
      "evSpd": 3,
      "evolutions": [],
      "experienceType": 2,
      "baseExperience": 295,
      "baseLoyalty": 0,
      "catchRate": 10,
      "femaleRate": -1,
      "breedGroups": [],
      "hatchSteps": 6400,
      "babyDbSymbol": "ironboulder",
      "babyForm": 0,
      "itemHeld": [
        {
          "dbSymbol": "none",
          "chance": 0
        },
        {
          "dbSymbol": "none",
          "chance": 0
        }
      ],
      "abilities": [
        "quark_drive",
        "quark_drive",
        "quark_drive"
      ],
      "frontOffsetY": 0,
      "resources": {
        "icon": "1022",
        "iconShiny": "1022",
        "front": "1022",
        "back": "1022",
        "frontShiny": "1022",
        "backShiny": "1022",
        "frontF": "1022f",
        "backF": "1022f",
        "frontShinyF": "1022f",
        "backShinyF": "1022f",
        "footprint": "1022",
        "character": "1022",
        "characterF": "1022f",
        "characterShiny": "1022s",
        "characterShinyF": "1022fs",
        "cry": "1022cry.ogg",
        "hasFemale": false
      },
      "moveSet": [],
      "formTextId": {
        "name": 1308,
        "description": 0
      }
    }
  ]
}