{
  "klass": "Specie",
  "id": 798,
  "dbSymbol": "kartana",
  "forms": [
    {
      "form": 0,
      "height": 0.3,
      "weight": 0.1,
      "type1": "grass",
      "type2": "steel",
      "baseHp": 59,
      "baseAtk": 181,
      "baseDfe": 131,
      "baseAts": 59,
      "baseDfs": 31,
      "baseSpd": 109,
      "evHp": 0,
      "evAtk": 3,
      "evDfe": 0,
      "evAts": 0,
      "evDfs": 0,
      "evSpd": 0,
      "evolutions": [],
      "experienceType": 2,
      "baseExperience": 285,
      "baseLoyalty": 0,
      "catchRate": 45,
      "femaleRate": -1,
      "breedGroups": [
        15,
        0
      ],
      "hatchSteps": 15360,
      "babyDbSymbol": "kartana",
      "babyForm": 0,
      "itemHeld": [
        {
          "dbSymbol": "none",
          "chance": 0
        },
        {
          "dbSymbol": "none",
          "chance": 0
        }
      ],
      "abilities": [
        "beast_boost",
        "beast_boost",
        "beast_boost"
      ],
      "frontOffsetY": 0,
      "resources": {
        "icon": "0798_00",
        "iconShiny": "0798_00",
        "front": "0798_00",
        "back": "0798_00",
        "frontShiny": "0798_00",
        "backShiny": "0798_00",
        "frontF": "0798f_00",
        "backF": "0798f_00",
        "frontShinyF": "0798f_00",
        "backShinyF": "0798f_00",
        "footprint": "0798_00",
        "character": "0798_00",
        "characterF": "0798f_00",
        "characterShiny": "0798s_00",
        "characterShinyF": "0798fs_00",
        "cry": "0798cry_00.ogg",
        "hasFemale": false
      },
      "moveSet": [],
      "formTextId": {
        "name": 444,
        "description": 0
      }
    }
  ]
}