{
  "klass": "Specie",
  "id": 66,
  "dbSymbol": "machop",
  "forms": [
    {
      "form": 0,
      "height": 0.8,
      "weight": 19.5,
      "type1": "fighting",
      "type2": "__undef__",
      "baseHp": 70,
      "baseAtk": 80,
      "baseDfe": 50,
      "baseAts": 35,
      "baseDfs": 35,
      "baseSpd": 35,
      "evHp": 0,
      "evAtk": 1,
      "evDfe": 0,
      "evAts": 0,
      "evDfs": 0,
      "evSpd": 0,
      "evolutions": [
        {
          "dbSymbol": "machoke",
          "form": 0,
          "conditions": [
            {
              "type": "minLevel",
              "value": 28
            }
          ]
        }
      ],
      "experienceType": 3,
      "baseExperience": 61,
      "baseLoyalty": 50,
      "catchRate": 180,
      "femaleRate": 25.0,
      "breedGroups": [
        8,
        0
      ],
      "hatchSteps": 2560,
      "babyDbSymbol": "machop",
      "babyForm": 0,
      "itemHeld": [
        {
          "dbSymbol": "none",
          "chance": 0
        },
        {
          "dbSymbol": "none",
          "chance": 0
        }
      ],
      "abilities": [
        "guts",
        "no_guard",
        "steadfast"
      ],
      "frontOffsetY": 0,
      "resources": {
        "icon": "0066_00",
        "iconShiny": "0066_00",
        "front": "0066_00",
        "back": "0066_00",
        "frontShiny": "0066_00",
        "backShiny": "0066_00",
        "frontF": "0066f_00",
        "backF": "0066f_00",
        "frontShinyF": "0066f_00",
        "backShinyF": "0066f_00",
        "footprint": "0066_00",
        "character": "0066_00",
        "characterF": "0066f_00",
        "characterShiny": "0066s_00",
        "characterShinyF": "0066fs_00",
        "cry": "0066cry_00.ogg",
        "hasFemale": false
      },
      "moveSet": [],
      "formTextId": {
        "name": 515,
        "description": 0
      }
    }
  ]
}