{
  "klass": "Specie",
  "id": 32,
  "dbSymbol": "nidoranm",
  "forms": [
    {
      "form": 0,
      "height": 0.5,
      "weight": 9.0,
      "type1": "poison",
      "type2": "__undef__",
      "baseHp": 46,
      "baseAtk": 57,
      "baseDfe": 40,
      "baseAts": 40,
      "baseDfs": 40,
      "baseSpd": 50,
      "evHp": 0,
      "evAtk": 1,
      "evDfe": 0,
      "evAts": 0,
      "evDfs": 0,
      "evSpd": 0,
      "evolutions": [
        {
          "dbSymbol": "nidorino",
          "form": 0,
          "conditions": [
            {
              "type": "minLevel",
              "value": 16
            }
          ]
        }
      ],
      "experienceType": 3,
      "baseExperience": 55,
      "baseLoyalty": 50,
      "catchRate": 235,
      "femaleRate": 0.0,
      "breedGroups": [
        1,
        5
      ],
      "hatchSteps": 2560,
      "babyDbSymbol": "nidoranm",
      "babyForm": 0,
      "itemHeld": [
        {
          "dbSymbol": "none",
          "chance": 0
        },
        {
          "dbSymbol": "none",
          "chance": 0
        }
      ],
      "abilities": [
        "poison_point",
        "rivalry",
        "hustle"
      ],
      "frontOffsetY": 0,
      "resources": {
        "icon": "0032_00",
        "iconShiny": "0032_00",
        "front": "0032_00",
        "back": "0032_00",
        "frontShiny": "0032_00",
        "backShiny": "0032_00",
        "frontF": "0032f_00",
        "backF": "0032f_00",
        "frontShinyF": "0032f_00",
        "backShinyF": "0032f_00",
        "footprint": "0032_00",
        "character": "0032_00",
        "characterF": "0032f_00",
        "characterShiny": "0032s_00",
        "characterShinyF": "0032fs_00",
        "cry": "0032cry_00.ogg",
        "hasFemale": false
      },
      "moveSet": [],
      "formTextId": {
        "name": 612,
        "description": 0
      }
    }
  ]
}