{
  "klass": "Specie",
  "id": 862,
  "dbSymbol": "obstagoon",
  "forms": [
    {
      "form": 0,
      "height": 1.6,
      "weight": 46.0,
      "type1": "dark",
      "type2": "normal",
      "baseHp": 93,
      "baseAtk": 90,
      "baseDfe": 101,
      "baseAts": 60,
      "baseDfs": 81,
      "baseSpd": 95,
      "evHp": 0,
      "evAtk": 0,
      "evDfe": 3,
      "evAts": 0,
      "evDfs": 0,
      "evSpd": 0,
      "evolutions": [],
      "experienceType": 1,
      "baseExperience": 260,
      "baseLoyalty": 50,
      "catchRate": 45,
      "femaleRate": 50.0,
      "breedGroups": [
        5,
        0
      ],
      "hatchSteps": 1920,
      "babyDbSymbol": "obstagoon",
      "babyForm": 0,
      "itemHeld": [
        {
          "dbSymbol": "none",
          "chance": 0
        },
        {
          "dbSymbol": "none",
          "chance": 0
        }
      ],
      "abilities": [
        "reckless",
        "guts",
        "defiant"
      ],
      "frontOffsetY": 0,
      "resources": {
        "icon": "862",
        "iconShiny": "862",
        "front": "862",
        "back": "862",
        "frontShiny": "862",
        "backShiny": "862",
        "frontF": "862f",
        "backF": "862f",
        "frontShinyF": "862f",
        "backShinyF": "862f",
        "footprint": "862",
        "character": "862",
        "characterF": "862f",
        "characterShiny": "862s",
        "characterShinyF": "862fs",
        "cry": "862cry.ogg",
        "hasFemale": false
      },
      "moveSet": [],
      "formTextId": {
        "name": 1354,
        "description": 0
      }
    }
  ]
}