{
  "klass": "Specie",
  "id": 511,
  "dbSymbol": "pansage",
  "forms": [
    {
      "form": 0,
      "height": 0.6,
      "weight": 10.5,
      "type1": "grass",
      "type2": "__undef__",
      "baseHp": 50,
      "baseAtk": 53,
      "baseDfe": 48,
      "baseAts": 53,
      "baseDfs": 48,
      "baseSpd": 64,
      "evHp": 0,
      "evAtk": 0,
      "evDfe": 0,
      "evAts": 0,
      "evDfs": 0,
      "evSpd": 1,
      "evolutions": [
        {
          "dbSymbol": "simisage",
          "form": 0,
          "conditions": [
            {
              "type": "stone",
              "value": "leaf_stone"
            }
          ]
        }
      ],
      "experienceType": 1,
      "baseExperience": 63,
      "baseLoyalty": 70,
      "catchRate": 190,
      "femaleRate": 12.5,
      "breedGroups": [
        5,
        0
      ],
      "hatchSteps": 2560,
      "babyDbSymbol": "pansage",
      "babyForm": 0,
      "itemHeld": [
        {
          "dbSymbol": "none",
          "chance": 0
        },
        {
          "dbSymbol": "none",
          "chance": 0
        }
      ],
      "abilities": [
        "gluttony",
        "gluttony",
        "overgrow"
      ],
      "frontOffsetY": 0,
      "resources": {
        "icon": "0511_00",
        "iconShiny": "0511_00",
        "front": "0511_00",
        "back": "0511_00",
        "frontShiny": "0511_00",
        "backShiny": "0511_00",
        "frontF": "0511f_00",
        "backF": "0511f_00",
        "frontShinyF": "0511f_00",
        "backShinyF": "0511f_00",
        "footprint": "0511_00",
        "character": "0511_00",
        "characterF": "0511f_00",
        "characterShiny": "0511s_00",
        "characterShinyF": "0511fs_00",
        "cry": "0511cry_00.ogg",
        "hasFemale": false
      },
      "moveSet": [],
      "formTextId": {
        "name": 648,
        "description": 0
      }
    }
  ]
}