{
  "klass": "Specie",
  "id": 409,
  "dbSymbol": "rampardos",
  "forms": [
    {
      "form": 0,
      "height": 1.6,
      "weight": 102.5,
      "type1": "rock",
      "type2": "__undef__",
      "baseHp": 97,
      "baseAtk": 165,
      "baseDfe": 60,
      "baseAts": 65,
      "baseDfs": 50,
      "baseSpd": 58,
      "evHp": 0,
      "evAtk": 2,
      "evDfe": 0,
      "evAts": 0,
      "evDfs": 0,
      "evSpd": 0,
      "evolutions": [],
      "experienceType": 4,
      "baseExperience": 173,
      "baseLoyalty": 70,
      "catchRate": 45,
      "femaleRate": 12.5,
      "breedGroups": [
        1,
        0
      ],
      "hatchSteps": 3840,
      "babyDbSymbol": "rampardos",
      "babyForm": 0,
      "itemHeld": [
        {
          "dbSymbol": "none",
          "chance": 0
        },
        {
          "dbSymbol": "none",
          "chance": 0
        }
      ],
      "abilities": [
        "mold_breaker",
        "mold_breaker",
        "sheer_force"
      ],
      "frontOffsetY": 0,
      "resources": {
        "icon": "409",
        "iconShiny": "409",
        "front": "409",
        "back": "409",
        "frontShiny": "409",
        "backShiny": "409",
        "frontF": "409f",
        "backF": "409f",
        "frontShinyF": "409f",
        "backShinyF": "409f",
        "footprint": "409",
        "character": "409",
        "characterF": "409f",
        "characterShiny": "409s",
        "characterShinyF": "409fs",
        "cry": "409cry.ogg",
        "hasFemale": false
      },
      "moveSet": [
        {
          "move": "fire_punch",
          "klass": "TechLearnableMove"
        },
        {
          "move": "thunder_punch",
          "klass": "TechLearnableMove"
        },
        {
          "move": "swords_dance",
          "klass": "TechLearnableMove"
        },
        {
          "move": "whirlwind",
          "klass": "BreedLearnableMove"
        },
        {
          "move": "slam",
          "klass": "LevelLearnableMove",
          "level": 28
        },
        {
          "move": "stomp",
          "klass": "BreedLearnableMove"
        },
        {
          "move": "headbutt",
          "klass": "LevelLearnableMove",
          "level": 1
        },
        {
          "move": "body_slam",
          "klass": "TechLearnableMove"
        },
        {
          "move": "take_down",
          "klass": "LevelLearnableMove",
          "level": 15
        },
        {
          "move": "take_down",
          "klass": "TechLearnableMove"
        },
        {
          "move": "thrash",
          "klass": "BreedLearnableMove"
        },
        {
          "move": "double_edge",
          "klass": "TechLearnableMove"
        },
        {
          "move": "leer",
          "klass": "LevelLearnableMove",
          "level": 1
        },
        {
          "move": "roar",
          "klass": "TechLearnableMove"
        },
        {
          "move": "flamethrower",
          "klass": "TechLearnableMove"
        },
        {
          "move": "surf",
          "klass": "TechLearnableMove"
        },
        {
          "move": "ice_beam",
          "klass": "TechLearnableMove"
        },
        {
          "move": "blizzard",
          "klass": "TechLearnableMove"
        },
        {
          "move": "hyper_beam",
          "klass": "TechLearnableMove"
        },
        {
          "move": "thunderbolt",
          "klass": "TechLearnableMove"
        },
        {
          "move": "thunder",
          "klass": "TechLearnableMove"
        },
        {
          "move": "earthquake",
          "klass": "TechLearnableMove"
        },
        {
          "move": "dig",
          "klass": "TechLearnableMove"
        },
        {
          "move": "screech",
          "klass": "LevelLearnableMove",
          "level": 51
        },
        {
          "move": "focus_energy",
          "klass": "LevelLearnableMove",
          "level": 1
        },
        {
          "move": "fire_blast",
          "klass": "TechLearnableMove"
        },
        {
          "move": "rest",
          "klass": "TechLearnableMove"
        },
        {
          "move": "rock_slide",
          "klass": "TechLearnableMove"
        },
        {
          "move": "substitute",
          "klass": "TechLearnableMove"
        },
        {
          "move": "thief",
          "klass": "TechLearnableMove"
        },
        {
          "move": "curse",
          "klass": "TechLearnableMove"
        },
        {
          "move": "protect",
          "klass": "TechLearnableMove"
        },
        {
          "move": "scary_face",
          "klass": "LevelLearnableMove",
          "level": 19
        },
        {
          "move": "scary_face",
          "klass": "TechLearnableMove"
        },
        {
          "move": "mud_slap",
          "klass": "TechLearnableMove"
        },
        {
          "move": "outrage",
          "klass": "TechLearnableMove"
        },
        {
          "move": "sandstorm",
          "klass": "TechLearnableMove"
        },
        {
          "move": "endure",
          "klass": "TechLearnableMove"
        },
        {
          "move": "sleep_talk",
          "klass": "TechLearnableMove"
        },
        {
          "move": "rain_dance",
          "klass": "TechLearnableMove"
        },
        {
          "move": "sunny_day",
          "klass": "TechLearnableMove"
        },
        {
          "move": "crunch",
          "klass": "TechLearnableMove"
        },
        {
          "move": "ancient_power",
          "klass": "LevelLearnableMove",
          "level": 36
        },
        {
          "move": "rock_smash",
          "klass": "LevelLearnableMove",
          "level": 10
        },
        {
          "move": "uproar",
          "klass": "TechLearnableMove"
        },
        {
          "move": "facade",
          "klass": "TechLearnableMove"
        },
        {
          "move": "focus_punch",
          "klass": "TechLearnableMove"
        },
        {
          "move": "brick_break",
          "klass": "TechLearnableMove"
        },
        {
          "move": "endeavor",
          "klass": "LevelLearnableMove",
          "level": 0
        },
        {
          "move": "endeavor",
          "klass": "TechLearnableMove"
        },
        {
          "move": "rock_tomb",
          "klass": "TechLearnableMove"
        },
        {
          "move": "dragon_claw",
          "klass": "TechLearnableMove"
        },
        {
          "move": "rock_blast",
          "klass": "TechLearnableMove"
        },
        {
          "move": "hammer_arm",
          "klass": "BreedLearnableMove"
        },
        {
          "move": "assurance",
          "klass": "LevelLearnableMove",
          "level": 24
        },
        {
          "move": "fling",
          "klass": "TechLearnableMove"
        },
        {
          "move": "dragon_pulse",
          "klass": "TechLearnableMove"
        },
        {
          "move": "focus_blast",
          "klass": "TechLearnableMove"
        },
        {
          "move": "earth_power",
          "klass": "TechLearnableMove"
        },
        {
          "move": "giga_impact",
          "klass": "TechLearnableMove"
        },
        {
          "move": "avalanche",
          "klass": "TechLearnableMove"
        },
        {
          "move": "zen_headbutt",
          "klass": "LevelLearnableMove",
          "level": 43
        },
        {
          "move": "zen_headbutt",
          "klass": "TechLearnableMove"
        },
        {
          "move": "iron_head",
          "klass": "TechLearnableMove"
        },
        {
          "move": "stone_edge",
          "klass": "TechLearnableMove"
        },
        {
          "move": "stealth_rock",
          "klass": "TechLearnableMove"
        },
        {
          "move": "head_smash",
          "klass": "LevelLearnableMove",
          "level": 58
        },
        {
          "move": "smack_down",
          "klass": "TechLearnableMove"
        },
        {
          "move": "heavy_slam",
          "klass": "TechLearnableMove"
        },
        {
          "move": "bulldoze",
          "klass": "TechLearnableMove"
        },
        {
          "move": "dragon_tail",
          "klass": "TechLearnableMove"
        },
        {
          "move": "stomping_tantrum",
          "klass": "TechLearnableMove"
        },
        {
          "move": "body_press",
          "klass": "TechLearnableMove"
        },
        {
          "move": "breaking_swipe",
          "klass": "TechLearnableMove"
        },
        {
          "move": "tera_blast",
          "klass": "TechLearnableMove"
        },
        {
          "move": "trailblaze",
          "klass": "TechLearnableMove"
        },
        {
          "move": "dragon_cheer",
          "klass": "TechLearnableMove"
        },
        {
          "move": "supercell_slam",
          "klass": "TechLearnableMove"
        }
      ],
      "formTextId": {
        "name": 720,
        "description": 0
      }
    }
  ]
}