{
  "klass": "Specie",
  "id": 828,
  "dbSymbol": "thievul",
  "forms": [
    {
      "form": 0,
      "height": 1.2,
      "weight": 19.9,
      "type1": "dark",
      "type2": "__undef__",
      "baseHp": 70,
      "baseAtk": 58,
      "baseDfe": 58,
      "baseAts": 87,
      "baseDfs": 92,
      "baseSpd": 90,
      "evHp": 0,
      "evAtk": 0,
      "evDfe": 0,
      "evAts": 0,
      "evDfs": 2,
      "evSpd": 0,
      "evolutions": [],
      "experienceType": 0,
      "baseExperience": 159,
      "baseLoyalty": 50,
      "catchRate": 127,
      "femaleRate": 50.0,
      "breedGroups": [
        5,
        0
      ],
      "hatchSteps": 1920,
      "babyDbSymbol": "thievul",
      "babyForm": 0,
      "itemHeld": [
        {
          "dbSymbol": "none",
          "chance": 0
        },
        {
          "dbSymbol": "none",
          "chance": 0
        }
      ],
      "abilities": [
        "run_away",
        "unburden",
        "stakeout"
      ],
      "frontOffsetY": 0,
      "resources": {
        "icon": "0828_00",
        "iconShiny": "0828_00",
        "front": "0828_00",
        "back": "0828_00",
        "frontShiny": "0828_00",
        "backShiny": "0828_00",
        "frontF": "0828f_00",
        "backF": "0828f_00",
        "frontShinyF": "0828f_00",
        "backShinyF": "0828f_00",
        "footprint": "0828_00",
        "character": "0828_00",
        "characterF": "0828f_00",
        "characterShiny": "0828s_00",
        "characterShinyF": "0828fs_00",
        "cry": "0828cry_00.ogg",
        "hasFemale": false
      },
      "moveSet": [],
      "formTextId": {
        "name": 1462,
        "description": 0
      }
    }
  ]
}