{
  "klass": "Specie",
  "id": 413,
  "dbSymbol": "wormadam",
  "forms": [
    {
      "form": 0,
      "height": 0.5,
      "weight": 6.5,
      "type1": "bug",
      "type2": "grass",
      "baseHp": 60,
      "baseAtk": 59,
      "baseDfe": 85,
      "baseAts": 79,
      "baseDfs": 105,
      "baseSpd": 36,
      "evHp": 0,
      "evAtk": 0,
      "evDfe": 0,
      "evAts": 0,
      "evDfs": 2,
      "evSpd": 0,
      "evolutions": [],
      "experienceType": 1,
      "baseExperience": 148,
      "baseLoyalty": 70,
      "catchRate": 45,
      "femaleRate": 100.0,
      "breedGroups": [
        3,
        0
      ],
      "hatchSteps": 1920,
      "babyDbSymbol": "wormadam",
      "babyForm": 0,
      "itemHeld": [
        {
          "dbSymbol": "none",
          "chance": 0
        },
        {
          "dbSymbol": "none",
          "chance": 0
        }
      ],
      "abilities": [
        "anticipation",
        "anticipation",
        "overcoat"
      ],
      "frontOffsetY": 0,
      "resources": {
        "icon": "413",
        "iconShiny": "413",
        "front": "413",
        "back": "413",
        "frontShiny": "413",
        "backShiny": "413",
        "frontF": "413f",
        "backF": "413f",
        "frontShinyF": "413f",
        "backShinyF": "413f",
        "footprint": "413",
        "character": "413",
        "characterF": "413f",
        "characterShiny": "413s",
        "characterShinyF": "413fs",
        "cry": "413cry.ogg",
        "hasFemale": false
      },
      "moveSet": [],
      "formTextId": {
        "name": 1064,
        "description": 0
      }
    },
    {
      "form": 1,
      "height": 0.5,
      "weight": 6.5,
      "type1": "bug",
      "type2": "ground",
      "baseHp": 60,
      "baseAtk": 79,
      "baseDfe": 105,
      "baseAts": 59,
      "baseDfs": 85,
      "baseSpd": 36,
      "evHp": 0,
      "evAtk": 0,
      "evDfe": 2,
      "evAts": 0,
      "evDfs": 0,
      "evSpd": 0,
      "evolutions": [],
      "experienceType": 1,
      "baseExperience": 148,
      "baseLoyalty": 70,
      "catchRate": 45,
      "femaleRate": 100.0,
      "breedGroups": [
        3,
        0
      ],
      "hatchSteps": 1920,
      "babyDbSymbol": "wormadam",
      "babyForm": 0,
      "itemHeld": [
        {
          "dbSymbol": "none",
          "chance": 0
        },
        {
          "dbSymbol": "none",
          "chance": 0
        }
      ],
      "abilities": [
        "anticipation",
        "anticipation",
        "overcoat"
      ],
      "frontOffsetY": 0,
      "resources": {
        "icon": "413_01",
        "iconShiny": "413_01",
        "front": "413_01",
        "back": "413_01",
        "frontShiny": "413_01",
        "backShiny": "413_01",
        "frontF": "413f_01",
        "backF": "413f_01",
        "frontShinyF": "413f_01",
        "backShinyF": "413f_01",
        "footprint": "413_01",
        "character": "413_01",
        "characterF": "413f_01",
        "characterShiny": "413s_01",
        "characterShinyF": "413fs_01",
        "cry": "413cry_01.ogg",
        "hasFemale": false
      },
      "moveSet": [],
      "formTextId": {
        "name": 1065,
        "description": 0
      }
    },
    {
      "form": 2,
      "height": 0.5,
      "weight": 6.5,
      "type1": "bug",
      "type2": "steel",
      "baseHp": 60,
      "baseAtk": 69,
      "baseDfe": 95,
      "baseAts": 69,
      "baseDfs": 95,
      "baseSpd": 36,
      "evHp": 0,
      "evAtk": 0,
      "evDfe": 1,
      "evAts": 0,
      "evDfs": 1,
      "evSpd": 0,
      "evolutions": [],
      "experienceType": 1,
      "baseExperience": 148,
      "baseLoyalty": 70,
      "catchRate": 45,
      "femaleRate": 100.0,
      "breedGroups": [
        3,
        0
      ],
      "hatchSteps": 1920,
      "babyDbSymbol": "wormadam",
      "babyForm": 0,
      "itemHeld": [
        {
          "dbSymbol": "none",
          "chance": 0
        },
        {
          "dbSymbol": "none",
          "chance": 0
        }
      ],
      "abilities": [
        "anticipation",
        "anticipation",
        "overcoat"
      ],
      "frontOffsetY": 0,
      "resources": {
        "icon": "413_02",
        "iconShiny": "413_02",
        "front": "413_02",
        "back": "413_02",
        "frontShiny": "413_02",
        "backShiny": "413_02",
        "frontF": "413f_02",
        "backF": "413f_02",
        "frontShinyF": "413f_02",
        "backShinyF": "413f_02",
        "footprint": "413_02",
        "character": "413_02",
        "characterF": "413f_02",
        "characterShiny": "413s_02",
        "characterShinyF": "413fs_02",
        "cry": "413cry_02.ogg",
        "hasFemale": false
      },
      "moveSet": [],
      "formTextId": {
        "name": 1066,
        "description": 0
      }
    }
  ]
}