{
  "klass": "Specie",
  "id": 961,
  "dbSymbol": "wugtrio",
  "forms": [
    {
      "form": 0,
      "height": 1.2,
      "weight": 5.4,
      "type1": "water",
      "type2": "__undef__",
      "baseHp": 35,
      "baseAtk": 100,
      "baseDfe": 50,
      "baseAts": 50,
      "baseDfs": 70,
      "baseSpd": 120,
      "evHp": 0,
      "evAtk": 0,
      "evDfe": 0,
      "evAts": 0,
      "evDfs": 0,
      "evSpd": 2,
      "evolutions": [],
      "experienceType": 1,
      "baseExperience": 149,
      "baseLoyalty": 50,
      "catchRate": 50,
      "femaleRate": 50.0,
      "breedGroups": [
        9,
        0
      ],
      "hatchSteps": 2560,
      "babyDbSymbol": "wugtrio",
      "babyForm": 0,
      "itemHeld": [
        {
          "dbSymbol": "none",
          "chance": 0
        },
        {
          "dbSymbol": "none",
          "chance": 0
        }
      ],
      "abilities": [
        "gooey",
        "rattled",
        "sand_veil"
      ],
      "frontOffsetY": 0,
      "resources": {
        "icon": "961",
        "iconShiny": "961",
        "front": "961",
        "back": "961",
        "frontShiny": "961",
        "backShiny": "961",
        "frontF": "961f",
        "backF": "961f",
        "frontShinyF": "961f",
        "backShinyF": "961f",
        "footprint": "961",
        "character": "961",
        "characterF": "961f",
        "characterShiny": "961s",
        "characterShinyF": "961fs",
        "cry": "961cry.ogg",
        "hasFemale": false
      },
      "moveSet": [
        {
          "move": "slam",
          "klass": "LevelLearnableMove",
          "level": 16
        },
        {
          "move": "sand_attack",
          "klass": "LevelLearnableMove",
          "level": 1
        },
        {
          "move": "headbutt",
          "klass": "LevelLearnableMove",
          "level": 24
        },
        {
          "move": "wrap",
          "klass": "LevelLearnableMove",
          "level": 1
        },
        {
          "move": "take_down",
          "klass": "TechLearnableMove"
        },
        {
          "move": "water_gun",
          "klass": "LevelLearnableMove",
          "level": 1
        },
        {
          "move": "hydro_pump",
          "klass": "TechLearnableMove"
        },
        {
          "move": "surf",
          "klass": "TechLearnableMove"
        },
        {
          "move": "ice_beam",
          "klass": "TechLearnableMove"
        },
        {
          "move": "blizzard",
          "klass": "TechLearnableMove"
        },
        {
          "move": "hyper_beam",
          "klass": "TechLearnableMove"
        },
        {
          "move": "dig",
          "klass": "LevelLearnableMove",
          "level": 36
        },
        {
          "move": "dig",
          "klass": "TechLearnableMove"
        },
        {
          "move": "agility",
          "klass": "TechLearnableMove"
        },
        {
          "move": "swift",
          "klass": "TechLearnableMove"
        },
        {
          "move": "rest",
          "klass": "TechLearnableMove"
        },
        {
          "move": "substitute",
          "klass": "TechLearnableMove"
        },
        {
          "move": "protect",
          "klass": "TechLearnableMove"
        },
        {
          "move": "mud_slap",
          "klass": "LevelLearnableMove",
          "level": 1
        },
        {
          "move": "mud_slap",
          "klass": "TechLearnableMove"
        },
        {
          "move": "sandstorm",
          "klass": "TechLearnableMove"
        },
        {
          "move": "endure",
          "klass": "TechLearnableMove"
        },
        {
          "move": "sleep_talk",
          "klass": "TechLearnableMove"
        },
        {
          "move": "pain_split",
          "klass": "TechLearnableMove"
        },
        {
          "move": "rain_dance",
          "klass": "TechLearnableMove"
        },
        {
          "move": "whirlpool",
          "klass": "TechLearnableMove"
        },
        {
          "move": "facade",
          "klass": "TechLearnableMove"
        },
        {
          "move": "helping_hand",
          "klass": "TechLearnableMove"
        },
        {
          "move": "muddy_water",
          "klass": "TechLearnableMove"
        },
        {
          "move": "mud_shot",
          "klass": "TechLearnableMove"
        },
        {
          "move": "water_pulse",
          "klass": "LevelLearnableMove",
          "level": 20
        },
        {
          "move": "water_pulse",
          "klass": "TechLearnableMove"
        },
        {
          "move": "sucker_punch",
          "klass": "LevelLearnableMove",
          "level": 42
        },
        {
          "move": "earth_power",
          "klass": "TechLearnableMove"
        },
        {
          "move": "giga_impact",
          "klass": "TechLearnableMove"
        },
        {
          "move": "aqua_jet",
          "klass": "LevelLearnableMove",
          "level": 12
        },
        {
          "move": "foul_play",
          "klass": "TechLearnableMove"
        },
        {
          "move": "bulldoze",
          "klass": "TechLearnableMove"
        },
        {
          "move": "throat_chop",
          "klass": "LevelLearnableMove",
          "level": 48
        },
        {
          "move": "throat_chop",
          "klass": "TechLearnableMove"
        },
        {
          "move": "stomping_tantrum",
          "klass": "TechLearnableMove"
        },
        {
          "move": "liquidation",
          "klass": "LevelLearnableMove",
          "level": 54
        },
        {
          "move": "liquidation",
          "klass": "TechLearnableMove"
        },
        {
          "move": "tera_blast",
          "klass": "TechLearnableMove"
        },
        {
          "move": "triple_dive",
          "klass": "LevelLearnableMove",
          "level": 30
        },
        {
          "move": "chilling_water",
          "klass": "TechLearnableMove"
        }
      ],
      "formTextId": {
        "name": 1492,
        "description": 0
      }
    }
  ]
}